[
  {
    "id": "1",
    "carousel": [
      { "img": "/img/house1.jpg" },
      { "img": "/img/house4" },
      { "img": "/img/house4.jpg" },
      { "img": "/img/house4.jpg" }
    ],
    "title": "Premier Gardens Phase 2",
    "county": "Machakos",
    "status": "Available",
    "type": "Land",
    "productImg": "BHS .jpg",
   "price": 2100000,
   "priceRange": ["Affordable", "Premium"],
   "discount": 10,
    "country": "Kenya",
    "district": "Mombasa Road Area",
    "properties": 1,
    "featured": true,
    "new": true,
    "rent": false,
    "photo": ["land", "acreage", "scenery"],
    "video": ["land", "tour"],
    "bedBath": ["Acreage", "buying", "investing"],
    "ratingCount": 4,
    "rating": 5,
    "saleCount": 15,
    "category": ["buying", "investing"],
    "tag": [
      "Land",
      "Acreage",
      "Prime Location",
      "Investment",
      "Kenya",
      "Mombasa Road area",
      "Real Estate"
    ],
    "date": "October 15, 2023",
    "comments": 50,
    "location": "Naivasha, Rift Valley, Kenya",
    "description": {
      "title": "Land Description",
      "fullDescription": "This prime 5-acre plot in Naivasha offers stunning views and is ideal for residential development, farming, or commercial projects. Located in a serene environment, it is easily accessible and close to essential amenities. The land is fertile and flat, with access to water and electricity, making it a great investment for future growth. Ideal for developers looking to create eco-friendly resorts or anyone interested in land banking.",
      "shortDescription": "A 5-acre prime plot located in Naivasha, perfect for residential, farming, or commercial use. Accessible, flat terrain with scenic views."
    },
    "propertyDetails": {
      "propertyId": "KEN29",
      "area": 5, 
      "propertyStatus": "For Sale",
      "createdYear": null 
    },
    "factsAndFeatures": {
      "plotSize": "50 x 100",
      "waterAccess": "Available",
      "electricity": "Nearby connection available",
      "soilType": "Fertile soil",
      "accessRoad": "All-weather road access",
      "landTitle": "Freehold title"
    },

    "amenities1": [
      "Water Access",
      "Electricity",
      "All-Weather Road",
      "Fertile Soil"
    ],
    "amenities2": [
      "Scenic Views",
      "Farming Potential",
      "Near Tourist Attractions",
      "Close to Naivasha Town"
    ],
    "amenities3": [
      "Refrigerator",
      "Window Coverings",
      "Washer",
      "24x7 Security",
      "Indoor Game"
    ],
    "AmenitiesList": ["Dishwasher"],
    "agent": {
      "firstName": "BiBlia Housing",
      "lastName": "BiBlia Housing",
      "fullName": "BiBlia Housing",
      "type": "Property Seller",
      "img": "author.jpg",
      "designation": "Traveller/Photographer",
      "raiting": 3,
      "description": "Accesible roads,  200m from sememe primary, WEll developed neighbourhood"
     
    },

    "gallery": {
      "img1": "house1.jpg",
      "img2": "house.3jpg",
      "img3": "house4.jpg"
    },
    "propertyTypes": ["House", "Office Villa", "Luxary Home"]
  },





 




  {
    "id": "3",
    "carousel": [
      { "img": "house.jpg" },
      { "img": "house.jpg" },
      { "img": "house.jpg" },
      { "img": "house.jpg" }
    ],
    "title": "Royal Gardens Malili",
    "county": "Makueni",
    "status": "Available",
    "type": "Land",
    "productImg": "BHS CURRENT PROJECTS - PORTAL3.jpg",
    "price": 650000,
    "priceRange": ["High-End"],
    "discount": 5,
    "country": "Kenya",
    "district": "Konza Metropolis",
    "properties": 1,
    "featured": true,
    "new": true,
    "rent": false,
    "photo": ["land", "commercial", "acreage"],
    "video": ["land", "tour"],
    "bedBath": ["Acreage", "buying", "developing"],
    "ratingCount": 3,
    "rating": 4,
    "saleCount": 8,
    "category": ["buying", "development", "commercial"],
    "tag": [
      "Commercial Land",
      "Development Land",
      "Prime Location",
      "Kenya",
      "Konza Metropolis",
      "Real Estate"
    ],

    "date": "October 1, 2023",
    "comments": 30,
    "location": "Mombasa Road",
    "description": {
      "title": "Land Description",
      "fullDescription": "Epic property located off-Mombasa Road 2.5 km from Konza metropolis, Ideal for residential, commercial development and futuristic gains.",
      "shortDescription": "Epic property located off-Mombasa Road 2.5 km from Konza metropolis, Ideal for residential, commercial development and futuristic gains."
    },
    "propertyDetails": {
      "propertyId": "KEN50",
      "area": 50, 
      "propertyStatus": "For Sale",
     
      "createdYear": null 
    },
    "factsAndFeatures": {
      "plotSize": "50 X 100",
      "waterAccess": "Available",
      "electricity": "Available",
      "accessRoad": "Tarmac road access",
      "landTitle": "Freehold title"
    },

    "amenities1": [
      "Water Access",
      "Electricity",
      "Road Access"
    ],
    "amenities2": [
      "Strategic Location",
      "Near Konza Metropolis",
      "Commercial Potential"
    ],
    "amenities3": [
      "Flat Terrain",
      "Infrastructure Ready",
      "Great for Industrial Projects"
    ],
    "AmenitiesList": ["Investment Opportunity"],
    "agent": {
      "firstName": "BiBlia Housing",
      "lastName": "BiBlia Housing",
      "fullName": "BiBlia Housing",
      "type": "Land seller",
      "img": "author.jpg",
      "designation": "Commercial Property Specialist",
      "rating": 4,
      "description": "Specialist in commercial land and development opportunities in Machakos and Nairobi regions.",
      "social": ["FaTwitter", "FaFacebook", "FaLinkedIn"]
    },

    "gallery": {
      "img1": "14.jpg",
      "img2": "15.jpg",
      "img3": "16.jpg"
    },
    "propertyTypes": ["Commercial Land", "Industrial Land"]
  },


  {
    "id": "5",
    "carousel": [
      { "img": "35.jpg" },
      { "img": "31.jpg" },
      { "img": "32.jpg" },
      { "img": "33.jpg" }
    ],
    "title": "Oasis Malaa 1",
    "county": "Machakos",
    "status": "Available",
    "type": "Land",
    "productImg": "BHS CURRENT PROJECTS - PORTAL4.jpg",
    "price": 550000, 
    "priceRange": ["High-End"],
    "discount": 3,
    "country": "Kenya",
    "district": "4 km from Kangundo Road",
    "properties": 1,
    "featured": true,
    "new": true,
    "rent": false,
    "photo": ["land", "industrial", "acreage"],
    "video": ["land", "tour"],
    "bedBath": ["Acreage", "buying", "industrial"],
    "ratingCount": 4.3,
    "rating": 4.8,
    "saleCount": 12,
    "category": ["buying", "industrial", "development"],
 
    "tag": [
      "Industrial Land",
      "Development Land",
      "Prime Location",
      "Kenya",
      "Kangundo Road",
      "Real Estate"
    ],
    "date": "September 2, 2024",
    "comments": 40,
    "location": "Mlolongo, Machakos County, Kenya",
    "description": {
      "title": "Land Description",
      "fullDescription": "Residential development / Commercial land located  4km from kangundo road and 10 Minutes drive from Joska Town . It has a well developed neighbourhood. Hop in this amazing opportunity now, and build your future property.",
      "shortDescription": "Residential development / Commercial land located  4km from kangundo road and 10 Minutes drive from Joska Town . It has a well developed neighbourhood. Hop in this amazing opportunity now, and build your future property."
    },
    "propertyDetails": {
      "propertyId": "KEN90",
      "area": 30, 
      "propertyStatus": "For Sale",
      
      "createdYear": null
    },
    "factsAndFeatures": {
      "plotSize": "50 X 100",
      "waterAccess": "Available",
      "electricity": "Available",
      "accessRoad": "Tarmac road access",
      "landTitle": "Freehold title"
    },

    "amenities1": [
      "Water Access",
      "Electricity",
      "Flat Terrain"
    ],
    "amenities2": [
      "Near Main Highway",
      "Close to Airport",
      "Developed Infrastructure"
    ],
    "amenities3": [
      "Ideal for Large-Scale Industries",
      "Top Choice for Warehousing",
      "Investment Potential"
    ],
    "AmenitiesList": ["Industrial Growth Opportunity"],
    "agent": {
      "firstName": "BiBlia Housing",
      "lastName": "BiBlia Housing",
      "fullName": "BiBlia Housing",
      "type": "Industrial Land Agent",
      "img": "author.jpg",
      "designation": "Industrial Property Consultant",
      "rating": 4.8,
      "description": "Specialist in industrial land and large-scale property development.",
      "social": ["FaFacebook", "FaLinkedIn", "FaInstagram"]
    },

    "gallery": {
      "img1": "14.jpg",
      "img2": "15.jpg",
      "img3": "16.jpg"
    },
   "propertyTypes": ["Industrial Land", "Development Land"]
  }



  
 
]
